README.rst
setup.py
bruker2bart/cfl.py
bruker2bart/cli.py
bruker2bart/core.py
bruker2bart.egg-info/PKG-INFO
bruker2bart.egg-info/SOURCES.txt
bruker2bart.egg-info/dependency_links.txt
bruker2bart.egg-info/entry_points.txt
bruker2bart.egg-info/not-zip-safe
bruker2bart.egg-info/requires.txt
bruker2bart.egg-info/top_level.txt