Metadata-Version: 1.0
Name: bruker2bart
Version: 0.1.0.0
Summary: Bruker to BART data format conversion
Home-page: UNKNOWN
Author: Tomas Psorn
Author-email: tomaspsorn@isibrno.cz
License: MIT
Platform: UNKNOWN
